claranet4/__init__.py
claranet4/cli.py
claranet4/lib.py
claranet4-0.2.0.dist-info/LICENSE
claranet4-0.2.0.dist-info/METADATA
claranet4-0.2.0.dist-info/WHEEL
claranet4-0.2.0.dist-info/entry_points.txt
claranet4-0.2.0.dist-info/top_level.txt
claranet4-0.2.0.dist-info/RECORD
