Metadata-Version: 2.1
Name: claranet4
Version: 0.2.0
Summary: Barebones Bleak-based client for the Aranet4 sensor
License: MIT License
Keywords: aranet4
Classifier: Programming Language :: Python :: 3.10
Classifier: Environment :: Console
Classifier: License :: OSI Approved :: MIT License
Classifier: Natural Language :: English
Classifier: Operating System :: POSIX :: Linux
Classifier: Operating System :: MacOS
Requires-Python: >=3.10
License-File: LICENSE
Requires-Dist: bleak (>=0.19.1)
Requires-Dist: defopt (>=6.4.0)
